{
  "gitSyncId": "68b6f1134c3e6631ec5e22b7_9fd2c123-5158-439e-a74a-6c65e7d9e746",
  "id": "Mock Customer UI_instantiateProcess",
  "pluginId": "bonita-api-plugin",
  "pluginType": "API",
  "unpublishedAction": {
    "actionConfiguration": {
      "autoGeneratedHeaders": [
        {
          "key": "content-type",
          "value": "application/json"
        }
      ],
      "body": "{\n\t\"loanRequestInput\": {\n\t\tamount:{{Instantiation_Form.data.Amount_Input}},\n\t\ttermMonths:{{Instantiation_Form.data.TermMonths_Input}},\n\t\tpurpose:{{Instantiation_Form.data.Purpose_Input}},\n\t\tinternalScore: 0,\n\t\texternalSolvencyScore: 0,\n\t\tcreatedAt:{{moment().toISOString()}},\n\tupdatedAt: {{moment().toISOString()}},\ncustomer: {\n\tfirstname:{{Instantiation_Form.data.FirstName_Input}},\n\tlastname:{{Instantiation_Form.data.Lastname_Input}},\n\temail:{{Instantiation_Form.data.Email_Input}},\n\tphone:{{Instantiation_Form.data.Phone_Input}},\n\tcity:{{Instantiation_Form.data.City_Input}},\n\tpostalCode: {{Instantiation_Form.data.Postal_Code_Input}},\n\tstreet:{{Instantiation_Form.data.Street_Input}},\n\t}\n},\n\tattachmentsInput: {{Utils.files}}\n}",
      "bodyFormData": [],
      "encodeParamsToggle": true,
      "formData": {
        "apiContentType": "application/json"
      },
      "headers": [],
      "httpMethod": "POST",
      "httpVersion": "HTTP11",
      "paginationType": "NONE",
      "path": "/bpm/process/{{loanRequestProcessDef.data[0].id}}/instantiation",
      "pluginSpecifiedTemplates": [
        {
          "value": true
        }
      ],
      "queryParameters": [],
      "timeoutInMillisecond": 10000
    },
    "confirmBeforeExecute": false,
    "datasource": {
      "id": "Bonita API",
      "isAutoGenerated": false,
      "name": "Bonita API",
      "pluginId": "bonita-api-plugin"
    },
    "dynamicBindingPathList": [
      {
        "key": "body"
      },
      {
        "key": "path"
      }
    ],
    "name": "instantiateProcess",
    "pageId": "Mock Customer UI",
    "runBehaviour": "MANUAL",
    "userSetOnLoad": false
  }
}